datacaster/__init__.py
datacaster/annotation_tools.py
datacaster/classes.py
datacaster/exceptions.py
datacaster/value_cast.py
datacaster-0.11.0.dist-info/LICENSE
datacaster-0.11.0.dist-info/METADATA
datacaster-0.11.0.dist-info/WHEEL
datacaster-0.11.0.dist-info/top_level.txt
datacaster-0.11.0.dist-info/RECORD
